{
    "buildings": [
        {
            "position": {
                "x": 45.0,
                "y": 0.0,
                "z": 235.0
            },
            "size": {
                "x": 175.0000457763672,
                "y": 300.0,
                "z": 105.0
            },
            "orientation": {
                "x": 0.0,
                "y": 326.0,
                "z": 0.0
            },
            "diag": 204.08335876464845,
            "dz": {
                "x": -29.35763931274414,
                "y": 0.0,
                "z": 43.52446365356445
            },
            "dx": {
                "x": 72.5407943725586,
                "y": 0.0,
                "z": 48.929412841796878
            },
            "mu": 0.0,
            "normals": [
                {
                    "x": -0.5591931343078613,
                    "y": 0.0,
                    "z": 0.8290374279022217
                },
                {
                    "x": 0.8290374279022217,
                    "y": 0.0,
                    "z": 0.5591931343078613
                },
                {
                    "x": 0.5591931343078613,
                    "y": 0.0,
                    "z": -0.8290374279022217
                },
                {
                    "x": -0.8290374279022217,
                    "y": 0.0,
                    "z": -0.5591931343078613
                }
            ],
            "verts": [
                {
                    "x": 88.18315124511719,
                    "y": 0.0,
                    "z": 327.4538879394531
                },
                {
                    "x": 146.8984375,
                    "y": 0.0,
                    "z": 240.4049530029297
                },
                {
                    "x": 1.8168411254882813,
                    "y": 0.0,
                    "z": 142.54612731933595
                },
                {
                    "x": -56.898433685302737,
                    "y": 0.0,
                    "z": 229.59506225585938
                }
            ]
        },
        {
            "position": {
                "x": -381.0,
                "y": 0.0,
                "z": 0.0
            },
            "size": {
                "x": 91.0,
                "y": 175.0,
                "z": 91.0
            },
            "orientation": {
                "x": 0.0,
                "y": 0.0,
                "z": 0.0
            },
            "diag": 128.6934356689453,
            "dz": {
                "x": 0.0,
                "y": 0.0,
                "z": 45.5
            },
            "dx": {
                "x": 45.5,
                "y": 0.0,
                "z": 0.0
            },
            "mu": 0.0,
            "normals": [
                {
                    "x": 0.0,
                    "y": 0.0,
                    "z": 1.0
                },
                {
                    "x": 1.0,
                    "y": 0.0,
                    "z": 0.0
                },
                {
                    "x": 0.0,
                    "y": 0.0,
                    "z": -1.0
                },
                {
                    "x": -1.0,
                    "y": 0.0,
                    "z": 0.0
                }
            ],
            "verts": [
                {
                    "x": -335.5,
                    "y": 0.0,
                    "z": 45.5
                },
                {
                    "x": -335.5,
                    "y": 0.0,
                    "z": -45.5
                },
                {
                    "x": -426.5,
                    "y": 0.0,
                    "z": -45.5
                },
                {
                    "x": -426.5,
                    "y": 0.0,
                    "z": 45.5
                }
            ]
        },
        {
            "position": {
                "x": -443.8000183105469,
                "y": 0.0,
                "z": -276.5
            },
            "size": {
                "x": 147.0,
                "y": 260.0,
                "z": 315.0
            },
            "orientation": {
                "x": 0.0,
                "y": 31.999996185302736,
                "z": 0.0
            },
            "diag": 347.6118469238281,
            "dz": {
                "x": 83.46227264404297,
                "y": 0.0,
                "z": 133.5675811767578
            },
            "dx": {
                "x": 62.331539154052737,
                "y": 0.0,
                "z": -38.94906234741211
            },
            "mu": 0.0,
            "normals": [
                {
                    "x": 0.5299192070960999,
                    "y": 0.0,
                    "z": 0.8480481505393982
                },
                {
                    "x": 0.8480481505393982,
                    "y": 0.0,
                    "z": -0.5299192070960999
                },
                {
                    "x": -0.5299192070960999,
                    "y": 0.0,
                    "z": -0.8480481505393982
                },
                {
                    "x": -0.8480481505393982,
                    "y": 0.0,
                    "z": 0.5299192070960999
                }
            ],
            "verts": [
                {
                    "x": -298.0061950683594,
                    "y": 0.0,
                    "z": -181.88148498535157
                },
                {
                    "x": -464.93072509765627,
                    "y": 0.0,
                    "z": -449.0166320800781
                },
                {
                    "x": -589.5938110351563,
                    "y": 0.0,
                    "z": -371.1184997558594
                },
                {
                    "x": -422.6692810058594,
                    "y": 0.0,
                    "z": -103.98335266113281
                }
            ]
        },
        {
            "position": {
                "x": 329.0,
                "y": 0.0,
                "z": 417.8999938964844
            },
            "size": {
                "x": 315.0,
                "y": 270.0,
                "z": 105.0
            },
            "orientation": {
                "x": 0.0,
                "y": 44.999996185302737,
                "z": 0.0
            },
            "diag": 332.0391540527344,
            "dz": {
                "x": 37.123104095458987,
                "y": 0.0,
                "z": 37.12310791015625
            },
            "dx": {
                "x": 111.36932373046875,
                "y": 0.0,
                "z": -111.36930847167969
            },
            "mu": 0.0,
            "normals": [
                {
                    "x": 0.7071067690849304,
                    "y": 0.0,
                    "z": 0.7071068286895752
                },
                {
                    "x": 0.7071068286895752,
                    "y": 0.0,
                    "z": -0.7071067094802856
                },
                {
                    "x": -0.7071067690849304,
                    "y": 0.0,
                    "z": -0.7071068286895752
                },
                {
                    "x": -0.7071068286895752,
                    "y": 0.0,
                    "z": 0.7071067094802856
                }
            ],
            "verts": [
                {
                    "x": 477.492431640625,
                    "y": 0.0,
                    "z": 343.65380859375
                },
                {
                    "x": 403.2462158203125,
                    "y": 0.0,
                    "z": 269.4075927734375
                },
                {
                    "x": 180.507568359375,
                    "y": 0.0,
                    "z": 492.14617919921877
                },
                {
                    "x": 254.7537841796875,
                    "y": 0.0,
                    "z": 566.3923950195313
                }
            ]
        },
        {
            "position": {
                "x": -77.70000457763672,
                "y": 0.0,
                "z": -256.8999938964844
            },
            "size": {
                "x": 161.0,
                "y": 392.0,
                "z": 161.0
            },
            "orientation": {
                "x": 0.0,
                "y": 45.99999237060547,
                "z": 0.0
            },
            "diag": 227.68838500976563,
            "dz": {
                "x": 57.9068489074707,
                "y": 0.0,
                "z": 55.920005798339847
            },
            "dx": {
                "x": 55.920005798339847,
                "y": 0.0,
                "z": -57.9068489074707
            },
            "mu": 0.0,
            "normals": [
                {
                    "x": 0.7193397283554077,
                    "y": 0.0,
                    "z": 0.6946584582328796
                },
                {
                    "x": 0.6946584582328796,
                    "y": 0.0,
                    "z": -0.7193397283554077
                },
                {
                    "x": -0.7193397283554077,
                    "y": 0.0,
                    "z": -0.6946584582328796
                },
                {
                    "x": -0.6946584582328796,
                    "y": 0.0,
                    "z": 0.7193397283554077
                }
            ],
            "verts": [
                {
                    "x": 36.12685012817383,
                    "y": 0.0,
                    "z": -258.8868408203125
                },
                {
                    "x": -79.68685150146485,
                    "y": 0.0,
                    "z": -370.72686767578127
                },
                {
                    "x": -191.52685546875,
                    "y": 0.0,
                    "z": -254.9131622314453
                },
                {
                    "x": -75.71316528320313,
                    "y": 0.0,
                    "z": -143.07313537597657
                }
            ]
        },
        {
            "position": {
                "x": 282.0,
                "y": 0.0,
                "z": 105.0
            },
            "size": {
                "x": 175.00006103515626,
                "y": 420.0,
                "z": 175.00006103515626
            },
            "orientation": {
                "x": 0.0,
                "y": 22.9999942779541,
                "z": 0.0
            },
            "diag": 247.48745727539063,
            "dz": {
                "x": 34.1889762878418,
                "y": 0.0,
                "z": 80.54420471191406
            },
            "dx": {
                "x": 80.54420471191406,
                "y": 0.0,
                "z": -34.1889762878418
            },
            "mu": 0.0,
            "normals": [
                {
                    "x": 0.39073100686073305,
                    "y": 0.0,
                    "z": 0.9205048680305481
                },
                {
                    "x": 0.9205048680305481,
                    "y": 0.0,
                    "z": -0.39073100686073305
                },
                {
                    "x": -0.39073100686073305,
                    "y": 0.0,
                    "z": -0.9205048680305481
                },
                {
                    "x": -0.9205048680305481,
                    "y": 0.0,
                    "z": 0.39073100686073305
                }
            ],
            "verts": [
                {
                    "x": 396.733154296875,
                    "y": 0.0,
                    "z": 151.355224609375
                },
                {
                    "x": 328.355224609375,
                    "y": 0.0,
                    "z": -9.73318099975586
                },
                {
                    "x": 167.26681518554688,
                    "y": 0.0,
                    "z": 58.644771575927737
                },
                {
                    "x": 235.64476013183595,
                    "y": 0.0,
                    "z": 219.73318481445313
                }
            ]
        },
        {
            "position": {
                "x": 119.0,
                "y": 0.0,
                "z": -60.0
            },
            "size": {
                "x": 161.0,
                "y": 392.0,
                "z": 161.0
            },
            "orientation": {
                "x": 0.0,
                "y": 45.99999237060547,
                "z": 0.0
            },
            "diag": 227.68838500976563,
            "dz": {
                "x": 57.9068489074707,
                "y": 0.0,
                "z": 55.920005798339847
            },
            "dx": {
                "x": 55.920005798339847,
                "y": 0.0,
                "z": -57.9068489074707
            },
            "mu": 0.0,
            "normals": [
                {
                    "x": 0.7193397283554077,
                    "y": 0.0,
                    "z": 0.6946584582328796
                },
                {
                    "x": 0.6946584582328796,
                    "y": 0.0,
                    "z": -0.7193397283554077
                },
                {
                    "x": -0.7193397283554077,
                    "y": 0.0,
                    "z": -0.6946584582328796
                },
                {
                    "x": -0.6946584582328796,
                    "y": 0.0,
                    "z": 0.7193397283554077
                }
            ],
            "verts": [
                {
                    "x": 232.82684326171876,
                    "y": 0.0,
                    "z": -61.98684310913086
                },
                {
                    "x": 117.01315307617188,
                    "y": 0.0,
                    "z": -173.8268585205078
                },
                {
                    "x": 5.173145294189453,
                    "y": 0.0,
                    "z": -58.01315689086914
                },
                {
                    "x": 120.9868392944336,
                    "y": 0.0,
                    "z": 53.82685470581055
                }
            ]
        }
    ],
    "noFlyZones": [
        {
            "position": {
                "x": -191.05543518066407,
                "y": 0.0,
                "z": 216.4875030517578
            },
            "size": {
                "x": 708.1451416015625,
                "y": 340.0,
                "z": 945.2459106445313
            },
            "orientation": {
                "x": 0.0,
                "y": 0.0,
                "z": 0.0
            },
            "diag": 1181.083984375,
            "dz": {
                "x": 0.0,
                "y": 0.0,
                "z": 472.6229553222656
            },
            "dx": {
                "x": 354.07257080078127,
                "y": 0.0,
                "z": 0.0
            },
            "mu": 0.0,
            "normals": [
                {
                    "x": 0.0,
                    "y": 0.0,
                    "z": 1.0
                },
                {
                    "x": 1.0,
                    "y": 0.0,
                    "z": 0.0
                },
                {
                    "x": 0.0,
                    "y": 0.0,
                    "z": -1.0
                },
                {
                    "x": -1.0,
                    "y": 0.0,
                    "z": 0.0
                }
            ],
            "verts": [
                {
                    "x": 163.0171356201172,
                    "y": 0.0,
                    "z": 689.1104736328125
                },
                {
                    "x": 163.0171356201172,
                    "y": 0.0,
                    "z": -256.13543701171877
                },
                {
                    "x": -545.1279907226563,
                    "y": 0.0,
                    "z": -256.13543701171877
                },
                {
                    "x": -545.1279907226563,
                    "y": 0.0,
                    "z": 689.1104736328125
                }
            ]
        }
    ],
    "dronePositions": [
        {
            "x": -317.0,
            "y": 240.0,
            "z": -292.0
        }
    ],
    "origin": {
        "x": -317.0,
        "y": 240.0,
        "z": -292.0
    },
    "destination": {
        "x": 478.0,
        "y": 240.0,
        "z": 560.0
    },
    "onJob": true
}